tc_agent_exporter/__init__.py
tc_agent_exporter-0.1.2.dist-info/LICENSE
tc_agent_exporter-0.1.2.dist-info/METADATA
tc_agent_exporter-0.1.2.dist-info/WHEEL
tc_agent_exporter-0.1.2.dist-info/entry_points.txt
tc_agent_exporter-0.1.2.dist-info/top_level.txt
tc_agent_exporter-0.1.2.dist-info/RECORD
