Metadata-Version: 2.1
Name: tc-agent-exporter
Version: 0.1.2
Summary: Export teamcity agent data
Home-page: https://github.com/adesso-mobile/tc_agent_exporter
Author: adesso mobile solutions GmbH
Author-email: it-operations@adesso-mobile.de
License: UNKNOWN
Project-URL: Bug Tracker, https://github.com/adesso-mobile/tc_agent_exporter/issues
Platform: UNKNOWN
Classifier: Programming Language :: Python :: 3
Classifier: License :: OSI Approved :: MIT License
Classifier: Operating System :: OS Independent
Requires-Python: >=3.6
License-File: LICENSE
Requires-Dist: requests
Requires-Dist: prometheus-client
